elder_algorithm_booth.v
module algoritm_booth
#(	parameter WIDTH = 4 )
(
	input enable,
	input clock,
	input [WIDTH - 1 : 0] mpd, //MultiPlicanD
	input [WIDTH - 1 : 0] mpr, //MultiPlieR
	output reg [ (2 * WIDTH) - 1 : 0] res
);
	
	reg [WIDTH - 1 : 0] cnt;
	reg [2 * WIDTH + 1 : 0] A;
	reg [2 * WIDTH + 1 : 0] S;
	reg [2 * WIDTH + 1 : 0] P;
	reg flag1;
	reg shift;
	
	always @ ( posedge clock ) begin
		
		if( 1'b1 == enable ) begin
			A <= {mpd[WIDTH - 1], mpd, { (WIDTH + 1){1'b0} } };
			S <= {mpd[WIDTH - 1], mpd, { WIDTH{1'b0} } };
			P <= { { (WIDTH + 1){1'b0} }, mpr, 1'b0};
			cnt  <= 1'b0;
			flag1 <= 1'b0;
			shift <= 1'b0;
		end
		
		if( 1'b0 == enable ) begin
			flag1 <= 1'b1;
		end
		
		if( 1'b0 == flag1 ) begin
		
			if(cnt < WIDTH) begin
			
				if( !shift ) begin
				
					case(P[1:0])
						default:
							begin
								P <= P >> 1;
								cnt <= cnt + 1'b1;
							end
							
						2'b01:
							begin
								P <= P + A;
								shift <= 1'b1;
							end
						
						2'b10:
							begin
								P <= P + S;
								shift <= 1'b1;
							end
					endcase
				end
				
				if( shift ) begin
					P <= P >> 1;
					cnt <= cnt + 1'b1;
					shift <= 1'b0;
				end
			end
			
			if( cnt >= WIDTH ) begin
				res <= P[(2 * WIDTH) : 1];
			end
		end
	end
		
endmodule

simulation_icarus/testbench.v
`timescale 1 ns / 1 ns
// testbench is a module which only task is to test another module
// testbench is for simulation only, not for synthesis
module testbench;
   // input and output test signals
   reg en;
   reg clk;
   reg  [ 3:0 ] x, y;
   wire [ 7:0 ] z;
	wire [ 3:0 ] cnt;
	wire [ 8:0 ] P;
	wire [ 8:0 ] S;
	wire [ 8:0 ] A; 
 
   // create the instances of the modules you want to test
    algoritm_booth #( .WIDTH(4) ) CLA_dut(
        .enable ( en ),
        .clock ( clk ),
        .mpd ( x ),
        .mpr ( y ),
        .res( z ),
		.cnt( cnt ),
		.P( P ),
		.S( S ),
		.A( A )
    );
        
    //write test sequence
    initial begin
        x    = 4'b0000;
        y    = 4'b0000;
        clk = 1'b0;
		en = 1'b0;
		#50
		x = $urandom_range( 0, 15 );
		y = $urandom_range( 0, 15 );
		#10 en = 1'b1;
		#50
		x = $urandom_range( 0, 15 );
		y = $urandom_range( 0, 15 );
		#50
		x = $urandom_range( 0, 15 );
		y = $urandom_range( 0, 15 );
		#50
		x = 4'b0011;
		y = 4'b0011;;
		#50
		x = 4'b0110;
		y = 4'b0110;
				
		#400
      $finish;
    end
    
	always
		#1 clk = ~clk;
	   
    // do at the beginning of the simulation
    //  print signal values on every change
    initial 
        $monitor("Time:\t%g, x: %b, y: %b, z: %b",
                $time,
                x,
                y,
                z,
            );
            
    // do at the beginning of the simulation
    //configure signals dump for waveform's creation
    initial begin 
        $dumpfile("dump.vcd");
        $dumpvars(1);  //iverilog dump init
    end
    
endmodule

simulation_icarus/dump.vcd
$date
	Fri Apr 15 11:40:19 2022
$end
$version
	Icarus Verilog
$end
$timescale
	1ns
$end
$scope module testbench $end
$var wire 8 ! z [7:0] $end
$var wire 4 " cnt [3:0] $end
$var wire 9 # S [8:0] $end
$var wire 9 $ P [8:0] $end
$var wire 9 % A [8:0] $end
$var reg 1 & clk $end
$var reg 1 ' en $end
$var reg 4 ( x [3:0] $end
$var reg 4 ) y [3:0] $end
$upscope $end
$enddefinitions $end
#0
$dumpvars
b0 )
b0 (
0'
0&
bx %
bx $
bx #
bx "
bx !
$end
#1
1&
#2
0&
#3
b0 "
b0 $
b0 #
b0 %
1&
#4
0&
#5
1&
#6
0&
#7
1&
#8
0&
#9
1&
#10
0&
#11
1&
#12
0&
#13
1&
#14
0&
#15
1&
#16
0&
#17
1&
#18
0&
#19
1&
#20
0&
#21
1&
#22
0&
#23
1&
#24
0&
#25
1&
#26
0&
#27
1&
#28
0&
#29
1&
#30
0&
#31
1&
#32
0&
#33
1&
#34
0&
#35
1&
#36
0&
#37
1&
#38
0&
#39
1&
#40
0&
#41
1&
#42
0&
#43
1&
#44
0&
#45
1&
#46
0&
#47
1&
#48
0&
#49
1&
#50
0&
b100 )
b1001 (
#51
b1000 $
b11100000 #
b100100000 %
1&
#52
0&
#53
1&
#54
0&
#55
1&
#56
0&
#57
1&
#58
0&
#59
1&
#60
0&
1'
#61
1&
#62
0&
#63
1&
#64
0&
#65
b1 "
b100 $
1&
#66
0&
#67
1&
#68
0&
#69
b10 "
b10 $
1&
#70
0&
#71
b11100010 $
1&
#72
0&
#73
b11 "
b1110001 $
1&
#74
0&
#75
b110010001 $
1&
#76
0&
#77
b100 "
b111001000 $
1&
#78
0&
#79
b11100100 !
1&
#80
0&
#81
b0 "
b1000 $
1&
#82
0&
#83
1&
#84
0&
#85
b1 "
b100 $
1&
#86
0&
#87
1&
#88
0&
#89
b10 "
b10 $
1&
#90
0&
#91
b11100010 $
1&
#92
0&
#93
b11 "
b1110001 $
1&
#94
0&
#95
b110010001 $
1&
#96
0&
#97
b100 "
b111001000 $
1&
#98
0&
#99
1&
#100
0&
#101
b0 "
b1000 $
1&
#102
0&
#103
1&
#104
0&
#105
b1 "
b100 $
1&
#106
0&
#107
1&
#108
0&
#109
b10 "
b10 $
1&
#110
0&
b11 )
b0 (
#111
b11100010 $
1&
#112
0&
#113
b11 "
b1110001 $
1&
#114
0&
#115
b110010001 $
1&
#116
0&
#117
b100 "
b111001000 $
1&
#118
0&
#119
1&
#120
0&
#121
b0 "
b110 $
b0 #
b0 %
1&
#122
0&
#123
1&
#124
0&
#125
b1 "
b11 $
1&
#126
0&
#127
1&
#128
0&
#129
b10 "
b1 $
1&
#130
0&
#131
1&
#132
0&
#133
b11 "
b0 $
1&
#134
0&
#135
1&
#136
0&
#137
b100 "
1&
#138
0&
#139
b0 !
1&
#140
0&
#141
b0 "
b110 $
1&
#142
0&
#143
1&
#144
0&
#145
b1 "
b11 $
1&
#146
0&
#147
1&
#148
0&
#149
b10 "
b1 $
1&
#150
0&
#151
1&
#152
0&
#153
b11 "
b0 $
1&
#154
0&
#155
1&
#156
0&
#157
b100 "
1&
#158
0&
#159
1&
#160
0&
b1100 )
b1000 (
#161
b0 "
b11000 $
b100000000 #
b100000000 %
1&
#162
0&
#163
1&
#164
0&
#165
b1 "
b1100 $
1&
#166
0&
#167
1&
#168
0&
#169
b10 "
b110 $
1&
#170
0&
#171
b100000110 $
1&
#172
0&
#173
b11 "
b110000011 $
1&
#174
0&
#175
1&
#176
0&
#177
b100 "
b111000001 $
1&
#178
0&
#179
b11100000 !
1&
#180
0&
#181
b0 "
b11000 $
1&
#182
0&
#183
1&
#184
0&
#185
b1 "
b1100 $
1&
#186
0&
#187
1&
#188
0&
#189
b10 "
b110 $
1&
#190
0&
#191
b100000110 $
1&
#192
0&
#193
b11 "
b110000011 $
1&
#194
0&
#195
1&
#196
0&
#197
b100 "
b111000001 $
1&
#198
0&
#199
1&
#200
0&
#201
b0 "
b11000 $
1&
#202
0&
#203
1&
#204
0&
#205
b1 "
b1100 $
1&
#206
0&
#207
1&
#208
0&
#209
b10 "
b110 $
1&
#210
0&
b11 )
b11 (
#211
b100000110 $
1&
#212
0&
#213
b11 "
b110000011 $
1&
#214
0&
#215
1&
#216
0&
#217
b100 "
b111000001 $
1&
#218
0&
#219
1&
#220
0&
#221
b0 "
b110 $
b110100000 #
b1100000 %
1&
#222
0&
#223
b110100110 $
1&
#224
0&
#225
b1 "
b111010011 $
1&
#226
0&
#227
1&
#228
0&
#229
b10 "
b111101001 $
1&
#230
0&
#231
b1001001 $
1&
#232
0&
#233
b11 "
b100100 $
1&
#234
0&
#235
1&
#236
0&
#237
b100 "
b10010 $
1&
#238
0&
#239
b1001 !
1&
#240
0&
#241
b0 "
b110 $
1&
#242
0&
#243
b110100110 $
1&
#244
0&
#245
b1 "
b111010011 $
1&
#246
0&
#247
1&
#248
0&
#249
b10 "
b111101001 $
1&
#250
0&
#251
b1001001 $
1&
#252
0&
#253
b11 "
b100100 $
1&
#254
0&
#255
1&
#256
0&
#257
b100 "
b10010 $
1&
#258
0&
#259
1&
#260
0&
b110 )
b110 (
#261
b0 "
b1100 $
b101000000 #
b11000000 %
1&
#262
0&
#263
1&
#264
0&
#265
b1 "
b110 $
1&
#266
0&
#267
b101000110 $
1&
#268
0&
#269
b10 "
b110100011 $
1&
#270
0&
#271
1&
#272
0&
#273
b11 "
b111010001 $
1&
#274
0&
#275
b10010001 $
1&
#276
0&
#277
b100 "
b1001000 $
1&
#278
0&
#279
b100100 !
1&
#280
0&
#281
b0 "
b1100 $
1&
#282
0&
#283
1&
#284
0&
#285
b1 "
b110 $
1&
#286
0&
#287
b101000110 $
1&
#288
0&
#289
b10 "
b110100011 $
1&
#290
0&
#291
1&
#292
0&
#293
b11 "
b111010001 $
1&
#294
0&
#295
b10010001 $
1&
#296
0&
#297
b100 "
b1001000 $
1&
#298
0&
#299
1&
#300
0&
#301
b0 "
b1100 $
1&
#302
0&
#303
1&
#304
0&
#305
b1 "
b110 $
1&
#306
0&
#307
b101000110 $
1&
#308
0&
#309
b10 "
b110100011 $
1&
#310
0&
#311
1&
#312
0&
#313
b11 "
b111010001 $
1&
#314
0&
#315
b10010001 $
1&
#316
0&
#317
b100 "
b1001000 $
1&
#318
0&
#319
1&
#320
0&
#321
b0 "
b1100 $
1&
#322
0&
#323
1&
#324
0&
#325
b1 "
b110 $
1&
#326
0&
#327
b101000110 $
1&
#328
0&
#329
b10 "
b110100011 $
1&
#330
0&
#331
1&
#332
0&
#333
b11 "
b111010001 $
1&
#334
0&
#335
b10010001 $
1&
#336
0&
#337
b100 "
b1001000 $
1&
#338
0&
#339
1&
#340
0&
#341
b0 "
b1100 $
1&
#342
0&
#343
1&
#344
0&
#345
b1 "
b110 $
1&
#346
0&
#347
b101000110 $
1&
#348
0&
#349
b10 "
b110100011 $
1&
#350
0&
#351
1&
#352
0&
#353
b11 "
b111010001 $
1&
#354
0&
#355
b10010001 $
1&
#356
0&
#357
b100 "
b1001000 $
1&
#358
0&
#359
1&
#360
0&
#361
b0 "
b1100 $
1&
#362
0&
#363
1&
#364
0&
#365
b1 "
b110 $
1&
#366
0&
#367
b101000110 $
1&
#368
0&
#369
b10 "
b110100011 $
1&
#370
0&
#371
1&
#372
0&
#373
b11 "
b111010001 $
1&
#374
0&
#375
b10010001 $
1&
#376
0&
#377
b100 "
b1001000 $
1&
#378
0&
#379
1&
#380
0&
#381
b0 "
b1100 $
1&
#382
0&
#383
1&
#384
0&
#385
b1 "
b110 $
1&
#386
0&
#387
b101000110 $
1&
#388
0&
#389
b10 "
b110100011 $
1&
#390
0&
#391
1&
#392
0&
#393
b11 "
b111010001 $
1&
#394
0&
#395
b10010001 $
1&
#396
0&
#397
b100 "
b1001000 $
1&
#398
0&
#399
1&
#400
0&
#401
b0 "
b1100 $
1&
#402
0&
#403
1&
#404
0&
#405
b1 "
b110 $
1&
#406
0&
#407
b101000110 $
1&
#408
0&
#409
b10 "
b110100011 $
1&
#410
0&
#411
1&
#412
0&
#413
b11 "
b111010001 $
1&
#414
0&
#415
b10010001 $
1&
#416
0&
#417
b100 "
b1001000 $
1&
#418
0&
#419
1&
#420
0&
#421
b0 "
b1100 $
1&
#422
0&
#423
1&
#424
0&
#425
b1 "
b110 $
1&
#426
0&
#427
b101000110 $
1&
#428
0&
#429
b10 "
b110100011 $
1&
#430
0&
#431
1&
#432
0&
#433
b11 "
b111010001 $
1&
#434
0&
#435
b10010001 $
1&
#436
0&
#437
b100 "
b1001000 $
1&
#438
0&
#439
1&
#440
0&
#441
b0 "
b1100 $
1&
#442
0&
#443
1&
#444
0&
#445
b1 "
b110 $
1&
#446
0&
#447
b101000110 $
1&
#448
0&
#449
b10 "
b110100011 $
1&
#450
0&
#451
1&
#452
0&
#453
b11 "
b111010001 $
1&
#454
0&
#455
b10010001 $
1&
#456
0&
#457
b100 "
b1001000 $
1&
#458
0&
#459
1&
#460
0&
#461
b0 "
b1100 $
1&
#462
0&
#463
1&
#464
0&
#465
b1 "
b110 $
1&
#466
0&
#467
b101000110 $
1&
#468
0&
#469
b10 "
b110100011 $
1&
#470
0&
#471
1&
#472
0&
#473
b11 "
b111010001 $
1&
#474
0&
#475
b10010001 $
1&
#476
0&
#477
b100 "
b1001000 $
1&
#478
0&
#479
1&
#480
0&
#481
b0 "
b1100 $
1&
#482
0&
#483
1&
#484
0&
#485
b1 "
b110 $
1&
#486
0&
#487
b101000110 $
1&
#488
0&
#489
b10 "
b110100011 $
1&
#490
0&
#491
1&
#492
0&
#493
b11 "
b111010001 $
1&
#494
0&
#495
b10010001 $
1&
#496
0&
#497
b100 "
b1001000 $
1&
#498
0&
#499
1&
#500
0&
#501
b0 "
b1100 $
1&
#502
0&
#503
1&
#504
0&
#505
b1 "
b110 $
1&
#506
0&
#507
b101000110 $
1&
#508
0&
#509
b10 "
b110100011 $
1&
#510
0&
#511
1&
#512
0&
#513
b11 "
b111010001 $
1&
#514
0&
#515
b10010001 $
1&
#516
0&
#517
b100 "
b1001000 $
1&
#518
0&
#519
1&
#520
0&
#521
b0 "
b1100 $
1&
#522
0&
#523
1&
#524
0&
#525
b1 "
b110 $
1&
#526
0&
#527
b101000110 $
1&
#528
0&
#529
b10 "
b110100011 $
1&
#530
0&
#531
1&
#532
0&
#533
b11 "
b111010001 $
1&
#534
0&
#535
b10010001 $
1&
#536
0&
#537
b100 "
b1001000 $
1&
#538
0&
#539
1&
#540
0&
#541
b0 "
b1100 $
1&
#542
0&
#543
1&
#544
0&
#545
b1 "
b110 $
1&
#546
0&
#547
b101000110 $
1&
#548
0&
#549
b10 "
b110100011 $
1&
#550
0&
#551
1&
#552
0&
#553
b11 "
b111010001 $
1&
#554
0&
#555
b10010001 $
1&
#556
0&
#557
b100 "
b1001000 $
1&
#558
0&
#559
1&
#560
0&
#561
b0 "
b1100 $
1&
#562
0&
#563
1&
#564
0&
#565
b1 "
b110 $
1&
#566
0&
#567
b101000110 $
1&
#568
0&
#569
b10 "
b110100011 $
1&
#570
0&
#571
1&
#572
0&
#573
b11 "
b111010001 $
1&
#574
0&
#575
b10010001 $
1&
#576
0&
#577
b100 "
b1001000 $
1&
#578
0&
#579
1&
#580
0&
#581
b0 "
b1100 $
1&
#582
0&
#583
1&
#584
0&
#585
b1 "
b110 $
1&
#586
0&
#587
b101000110 $
1&
#588
0&
#589
b10 "
b110100011 $
1&
#590
0&
#591
1&
#592
0&
#593
b11 "
b111010001 $
1&
#594
0&
#595
b10010001 $
1&
#596
0&
#597
b100 "
b1001000 $
1&
#598
0&
#599
1&
#600
0&
#601
b0 "
b1100 $
1&
#602
0&
#603
1&
#604
0&
#605
b1 "
b110 $
1&
#606
0&
#607
b101000110 $
1&
#608
0&
#609
b10 "
b110100011 $
1&
#610
0&
#611
1&
#612
0&
#613
b11 "
b111010001 $
1&
#614
0&
#615
b10010001 $
1&
#616
0&
#617
b100 "
b1001000 $
1&
#618
0&
#619
1&
#620
0&
#621
b0 "
b1100 $
1&
#622
0&
#623
1&
#624
0&
#625
b1 "
b110 $
1&
#626
0&
#627
b101000110 $
1&
#628
0&
#629
b10 "
b110100011 $
1&
#630
0&
#631
1&
#632
0&
#633
b11 "
b111010001 $
1&
#634
0&
#635
b10010001 $
1&
#636
0&
#637
b100 "
b1001000 $
1&
#638
0&
#639
1&
#640
0&
#641
b0 "
b1100 $
1&
#642
0&
#643
1&
#644
0&
#645
b1 "
b110 $
1&
#646
0&
#647
b101000110 $
1&
#648
0&
#649
b10 "
b110100011 $
1&
#650
0&
#651
1&
#652
0&
#653
b11 "
b111010001 $
1&
#654
0&
#655
b10010001 $
1&
#656
0&
#657
b100 "
b1001000 $
1&
